{
  "todos": [
    {
      "id": 20,
      "title": "json-server",
      "status": false
    },
    {
      "title": "a",
      "status": false,
      "id": 1
    },
    {
      "title": "Moazzem",
      "status": false,
      "id": 3
    },
    {
      "title": "hosen",
      "status": false,
      "id": 4
    },
    {
      "title": "hosensardar",
      "status": false,
      "id": 5
    },
    {
      "title": "hosensardar1",
      "status": false,
      "id": 6
    },
    {
      "title": "rrr",
      "status": false,
      "id": 7
    }
  ]
}